{
    "data": [
        {   
            "house_id":1,
            "url": "http://127.0.0.1:7890/img/pic07.jpg",   
            "house_name":"鹏展汇",
            "sites_info":"宝安区 | 沙井",
            "price":45000,
            "tags":"低单价,新盘首开",
            "city":"深圳"
        },
        {   
            "house_id":2,
            "url": "http://127.0.0.1:7890/img/pic08.jpg",   
            "house_name":"建业擎天",
            "sites_info":"龙岗区 | 横岗",
            "price":62000,
            "tags":"购物方便,美食云集",
            "city":"深圳"
        },
        {   
            "house_id":3,
            "url": "http://127.0.0.1:7890/img/pic09.jpg",   
            "house_name":"金阳湖畔",
            "sites_info":"北京 | 燕郊",
            "price":55000,
            "tags":"低单价,环境优美",
            "city":"北京"
        },
        {   
            "house_id":4,
            "url": "http://127.0.0.1:7890/img/pic10.jpg",   
            "house_name":"国彩立方",
            "sites_info":"北京 | 昌平",
            "price":62000,
            "tags":"购物方便,地铁口旁",
            "city":"北京"

        }
    ],
    "code":200,
    "msg":"首页新房数据"
}